minimal_package/__init__.py
minimal_package/minimal_module.py
minimal_project-0.1.1.dist-info/METADATA
minimal_project-0.1.1.dist-info/WHEEL
minimal_project-0.1.1.dist-info/top_level.txt
minimal_project-0.1.1.dist-info/RECORD
