Metadata-Version: 2.1
Name: minimal_project
Version: 0.1.1
Summary: A minimal Python package
Home-page: https://github.com/Chandra158/minimal-project
Author: Chandra Prakash
Author-email: chandra.pr.158@gmail.com
License: MIT
Classifier: Programming Language :: Python :: 3
Classifier: License :: OSI Approved :: MIT License
Classifier: Operating System :: OS Independent
Requires-Python: >=3.6
